LICENSE
README.md
setup.cfg
setup.py
penninitez/__init__.py
penninitez/main.py
penninitez.egg-info/PKG-INFO
penninitez.egg-info/SOURCES.txt
penninitez.egg-info/dependency_links.txt
penninitez.egg-info/requires.txt
penninitez.egg-info/top_level.txt